lakesuperior/__init__.py
lakesuperior/app.py
lakesuperior/config_parser.py
lakesuperior/env_setup.py
lakesuperior/exceptions.py
lakesuperior/globals.py
lakesuperior/lsup_admin.py
lakesuperior/migrator.py
lakesuperior/profiler.py
lakesuperior/server.py
lakesuperior/toolbox.py
lakesuperior/wsgi.py
lakesuperior/api/__init__.py
lakesuperior/api/admin.py
lakesuperior/api/query.py
lakesuperior/api/resource.py
lakesuperior/data/bootstrap/rsrc_centric_layout.sparql
lakesuperior/dictionaries/__init__.py
lakesuperior/dictionaries/namespaces.py
lakesuperior/dictionaries/srv_mgd_terms.py
lakesuperior/endpoints/__init__.py
lakesuperior/endpoints/admin.py
lakesuperior/endpoints/ldp.py
lakesuperior/endpoints/main.py
lakesuperior/endpoints/query.py
lakesuperior/endpoints/templates/admin_tools.html
lakesuperior/endpoints/templates/base.html
lakesuperior/endpoints/templates/index.html
lakesuperior/endpoints/templates/namespaces.html
lakesuperior/endpoints/templates/navbar.html
lakesuperior/endpoints/templates/resource.html
lakesuperior/endpoints/templates/sparql_query.html
lakesuperior/endpoints/templates/stats.html
lakesuperior/endpoints/templates/term_search.html
lakesuperior/endpoints/templates/static/assets/css/bootstrap.min.css
lakesuperior/endpoints/templates/static/assets/css/yasgui.min.css
lakesuperior/endpoints/templates/static/assets/fonts/glyphicons-halflings-regular.eot
lakesuperior/endpoints/templates/static/assets/fonts/glyphicons-halflings-regular.svg
lakesuperior/endpoints/templates/static/assets/fonts/glyphicons-halflings-regular.ttf
lakesuperior/endpoints/templates/static/assets/fonts/glyphicons-halflings-regular.woff
lakesuperior/endpoints/templates/static/assets/fonts/glyphicons-halflings-regular.woff2
lakesuperior/endpoints/templates/static/assets/js/bootstrap.bundle.min.js
lakesuperior/endpoints/templates/static/assets/js/jquery-3.2.1.min.js
lakesuperior/endpoints/templates/static/assets/js/npm.js
lakesuperior-1.0.0a17.dist-info/METADATA
lakesuperior-1.0.0a17.dist-info/RECORD
lakesuperior-1.0.0a17.dist-info/WHEEL
lakesuperior-1.0.0a17.dist-info/entry_points.txt
lakesuperior-1.0.0a17.dist-info/top_level.txt
