Metadata-Version: 2.1
Name: lakesuperior
Version: 1.0.0a17
Summary: A Linked Data Platform repository sever.
Home-page: https://lakesuperior.readthedocs.io
Author: Stefano Cossu <@scossu>
License: Apache License Version 2.0
Project-URL: Discussion, https://groups.google.com/forum/#!forum/lakesuperior
Project-URL: Documentation, https://lakesuperior.readthedocs.io
Project-URL: Source Code, https://github.com/scossu/lakesuperior/
Project-URL: Bug Reports, https://github.com/scossu/lakesuperior/issues
Keywords: repository linked-data
Platform: UNKNOWN
Classifier: Development Status :: 3 - Alpha
Classifier: Environment :: Console
Classifier: Environment :: Web Environment
Classifier: Framework :: Flask
Classifier: Intended Audience :: Developers
Classifier: Intended Audience :: Information Technology
Classifier: Intended Audience :: Science/Research
Classifier: License :: OSI Approved :: Apache Software License
Classifier: Natural Language :: English
Classifier: Operating System :: MacOS
Classifier: Operating System :: Microsoft :: Windows
Classifier: Operating System :: POSIX :: Linux
Classifier: Programming Language :: Python :: 3
Classifier: Programming Language :: Python :: 3.5
Classifier: Programming Language :: Python :: 3.6
Classifier: Topic :: Database :: Database Engines/Servers
Requires-Python: ~=3.5
Requires-Dist: CoilMQ
Requires-Dist: Flask
Requires-Dist: HiYaPyCo
Requires-Dist: PyYAML
Requires-Dist: arrow
Requires-Dist: cchardet
Requires-Dist: click
Requires-Dist: click-log
Requires-Dist: gevent
Requires-Dist: gunicorn
Requires-Dist: lmdb
Requires-Dist: rdflib
Requires-Dist: rdflib-jsonld
Requires-Dist: requests
Requires-Dist: requests-toolbelt
Requires-Dist: sphinx-rtd-theme
Requires-Dist: stomp.py
